mdakit_sasa/__init__.py
mdakit_sasa/_version.py
mdakit_sasa/analysis/__init__.py
mdakit_sasa/analysis/sasaanalysis.py
mdakit_sasa/tests/__init__.py
mdakit_sasa/tests/conftest.py
mdakit_sasa/tests/test_mdakit_sasa.py
mdakit_sasa/tests/utils.py
mdakit_sasa/tests/analysis/__init__.py
mdakit_sasa/tests/analysis/test_sasaanalysis.py
mdakit_sasa/tests/data/134L.pdb
mdakit_sasa/tests/data/image_vf.data
mdakit_sasa-0.2.7.dist-info/AUTHORS.md
mdakit_sasa-0.2.7.dist-info/LICENSE
mdakit_sasa-0.2.7.dist-info/METADATA
mdakit_sasa-0.2.7.dist-info/WHEEL
mdakit_sasa-0.2.7.dist-info/top_level.txt
mdakit_sasa-0.2.7.dist-info/RECORD
