Metadata-Version: 2.1
Name: mdakit_sasa
Version: 0.2.7
Summary: This kit allows the calculation of a solvent-accessible-surface area of a trajectory
Author: Pegerto Fernandez
Author-email: Pegerto Fernandez <pegerto.fernandez@brunel.ac.uk>
Maintainer-email: Pegerto Fernandez <pegerto.fernandez@brunel.ac.uk>
License: GNU GENERAL PUBLIC LICENSE
Keywords: molecular simulations
Requires-Python: >=3.9
License-File: LICENSE
License-File: AUTHORS.md
Requires-Dist: MDAnalysis>=2.0.0
Requires-Dist: freesasa>=2.2.0
Provides-Extra: doc
Requires-Dist: sphinx; extra == "doc"
Requires-Dist: sphinx-rtd-theme; extra == "doc"
Provides-Extra: test
Requires-Dist: pytest>=6.0; extra == "test"
Requires-Dist: pytest-xdist>=2.5; extra == "test"
Requires-Dist: pytest-cov>=3.0; extra == "test"
